odoo/addons/account_invoice_supplier_self_invoice/README.rst
odoo/addons/account_invoice_supplier_self_invoice/__init__.py
odoo/addons/account_invoice_supplier_self_invoice/__manifest__.py
odoo/addons/account_invoice_supplier_self_invoice/i18n/account_invoice_supplier_self_invoice.pot
odoo/addons/account_invoice_supplier_self_invoice/i18n/ar.po
odoo/addons/account_invoice_supplier_self_invoice/i18n/bg.po
odoo/addons/account_invoice_supplier_self_invoice/i18n/bs.po
odoo/addons/account_invoice_supplier_self_invoice/i18n/ca.po
odoo/addons/account_invoice_supplier_self_invoice/i18n/cs.po
odoo/addons/account_invoice_supplier_self_invoice/i18n/da.po
odoo/addons/account_invoice_supplier_self_invoice/i18n/de.po
odoo/addons/account_invoice_supplier_self_invoice/i18n/el_GR.po
odoo/addons/account_invoice_supplier_self_invoice/i18n/en_GB.po
odoo/addons/account_invoice_supplier_self_invoice/i18n/es.po
odoo/addons/account_invoice_supplier_self_invoice/i18n/es_AR.po
odoo/addons/account_invoice_supplier_self_invoice/i18n/es_CL.po
odoo/addons/account_invoice_supplier_self_invoice/i18n/es_CO.po
odoo/addons/account_invoice_supplier_self_invoice/i18n/es_CR.po
odoo/addons/account_invoice_supplier_self_invoice/i18n/es_DO.po
odoo/addons/account_invoice_supplier_self_invoice/i18n/es_EC.po
odoo/addons/account_invoice_supplier_self_invoice/i18n/es_ES.po
odoo/addons/account_invoice_supplier_self_invoice/i18n/es_MX.po
odoo/addons/account_invoice_supplier_self_invoice/i18n/es_PE.po
odoo/addons/account_invoice_supplier_self_invoice/i18n/es_PY.po
odoo/addons/account_invoice_supplier_self_invoice/i18n/es_VE.po
odoo/addons/account_invoice_supplier_self_invoice/i18n/et.po
odoo/addons/account_invoice_supplier_self_invoice/i18n/eu.po
odoo/addons/account_invoice_supplier_self_invoice/i18n/fa.po
odoo/addons/account_invoice_supplier_self_invoice/i18n/fi.po
odoo/addons/account_invoice_supplier_self_invoice/i18n/fr.po
odoo/addons/account_invoice_supplier_self_invoice/i18n/fr_CA.po
odoo13_addon_account_invoice_supplier_self_invoice-13.0.1.1.1.dist-info/METADATA
odoo13_addon_account_invoice_supplier_self_invoice-13.0.1.1.1.dist-info/WHEEL
odoo13_addon_account_invoice_supplier_self_invoice-13.0.1.1.1.dist-info/top_level.txt
odoo13_addon_account_invoice_supplier_self_invoice-13.0.1.1.1.dist-info/RECORD
